libssp_py/__init__.py
libssp_py/discovery.py
libssp_py/ssp.py
libssp_py/tests.py
libssp_py/util.py
libssp_py-0.0.2.dist-info/LICENSE
libssp_py-0.0.2.dist-info/METADATA
libssp_py-0.0.2.dist-info/WHEEL
libssp_py-0.0.2.dist-info/top_level.txt
libssp_py-0.0.2.dist-info/RECORD
