Metadata-Version: 2.1
Name: libssp-py
Version: 0.0.2
Summary: A pure Python implementation of the Simple Streaming protocol
Author-email: Miha Frangež <miha.ssp@derp.si>
Project-URL: Homepage, https://gitlab.com/franga2000/libssp_py
Project-URL: Bug Tracker, https://gitlab.com/franga2000/libssp_py/issues
Project-URL: Source Code, https://gitlab.com/franga2000/libssp_py
Classifier: Programming Language :: Python :: 3
Classifier: License :: OSI Approved :: GNU Lesser General Public License v3 (LGPLv3)
Classifier: Operating System :: OS Independent
Requires-Python: >=3.7
License-File: LICENSE
Provides-Extra: discovery
Requires-Dist: zeroconf ==0.74.0 ; extra == 'discovery'
